[
  {
    "review_timestamp": "2026-04-30T17:14:58.269625",
    "decision": "modify",
    "reviewer": "gui_autonomous_agent",
    "confidence": 0.8,
    "comments": "Auto-approved (GUI mode): High confidence (0.80) but success criteria not met",
    "modifications": [
      "Auto-generated modification (GUI mode)"
    ],
    "experiment_id": "attentional_blink_iter_0",
    "success_criteria_met": false,
    "auto_threshold": 0.7
  },
  {
    "review_timestamp": "2026-04-30T17:14:58.481888",
    "decision": "modify",
    "reviewer": "gui_autonomous_agent",
    "confidence": 0.8,
    "comments": "Auto-approved (GUI mode): High confidence (0.80) but success criteria not met",
    "modifications": [
      "Auto-generated modification (GUI mode)"
    ],
    "experiment_id": "attentional_blink_iter_1",
    "success_criteria_met": false,
    "auto_threshold": 0.7
  },
  {
    "review_timestamp": "2026-04-30T17:14:58.682753",
    "decision": "modify",
    "reviewer": "gui_autonomous_agent",
    "confidence": 0.8,
    "comments": "Auto-approved (GUI mode): High confidence (0.80) but success criteria not met",
    "modifications": [
      "Auto-generated modification (GUI mode)"
    ],
    "experiment_id": "attentional_blink_iter_2",
    "success_criteria_met": false,
    "auto_threshold": 0.7
  },
  {
    "review_timestamp": "2026-04-30T17:16:20.018255",
    "decision": "modify",
    "reviewer": "gui_autonomous_agent",
    "confidence": 0.8,
    "comments": "Auto-approved (GUI mode): High confidence (0.80) but success criteria not met",
    "modifications": [
      "Auto-generated modification (GUI mode)"
    ],
    "experiment_id": "working_memory_span_iter_0",
    "success_criteria_met": false,
    "auto_threshold": 0.7
  },
  {
    "review_timestamp": "2026-04-30T17:17:20.400522",
    "decision": "modify",
    "reviewer": "gui_autonomous_agent",
    "confidence": 0.8,
    "comments": "Auto-approved (GUI mode): High confidence (0.80) but success criteria not met",
    "modifications": [
      "Auto-generated modification (GUI mode)"
    ],
    "experiment_id": "working_memory_span_iter_1",
    "success_criteria_met": false,
    "auto_threshold": 0.7
  },
  {
    "review_timestamp": "2026-04-30T17:18:20.803446",
    "decision": "modify",
    "reviewer": "gui_autonomous_agent",
    "confidence": 0.8,
    "comments": "Auto-approved (GUI mode): High confidence (0.80) but success criteria not met",
    "modifications": [
      "Auto-generated modification (GUI mode)"
    ],
    "experiment_id": "working_memory_span_iter_2",
    "success_criteria_met": false,
    "auto_threshold": 0.7
  },
  {
    "review_timestamp": "2026-04-30T17:48:38.661467",
    "decision": "modify",
    "reviewer": "gui_autonomous_agent",
    "confidence": 0.8,
    "comments": "Auto-approved (GUI mode): High confidence (0.80) but success criteria not met",
    "modifications": [
      "Auto-generated modification (GUI mode)"
    ],
    "experiment_id": "attentional_blink_iter_0",
    "success_criteria_met": false,
    "auto_threshold": 0.7
  },
  {
    "review_timestamp": "2026-04-30T17:48:38.870594",
    "decision": "modify",
    "reviewer": "gui_autonomous_agent",
    "confidence": 0.8,
    "comments": "Auto-approved (GUI mode): High confidence (0.80) but success criteria not met",
    "modifications": [
      "Auto-generated modification (GUI mode)"
    ],
    "experiment_id": "attentional_blink_iter_1",
    "success_criteria_met": false,
    "auto_threshold": 0.7
  },
  {
    "review_timestamp": "2026-04-30T17:48:39.084486",
    "decision": "modify",
    "reviewer": "gui_autonomous_agent",
    "confidence": 0.8,
    "comments": "Auto-approved (GUI mode): High confidence (0.80) but success criteria not met",
    "modifications": [
      "Auto-generated modification (GUI mode)"
    ],
    "experiment_id": "attentional_blink_iter_2",
    "success_criteria_met": false,
    "auto_threshold": 0.7
  },
  {
    "review_timestamp": "2026-04-30T17:48:56.787669",
    "decision": "modify",
    "reviewer": "gui_autonomous_agent",
    "confidence": 0.8,
    "comments": "Auto-approved (GUI mode): High confidence (0.80) but success criteria not met",
    "modifications": [
      "Auto-generated modification (GUI mode)"
    ],
    "experiment_id": "change_blindness_iter_0",
    "success_criteria_met": false,
    "auto_threshold": 0.7
  }
]